{"kind":"identitytoolkit#DownloadAccountResponse","users":[{"localId":"MCLk8LeFnHoyHmngdNTHA2wk7mOb","createdAt":"1646356351436","lastLoginAt":"1646356351436","emailVerified":false,"email":"volunteer@test.com","salt":"fakeSaltHLHWBcTwhfzOWF22NVbp","passwordHash":"fakeHash:salt=fakeSaltHLHWBcTwhfzOWF22NVbp:password=volunteervolunteervolunteer","passwordUpdatedAt":1646356351436,"validSince":"1646356351","providerUserInfo":[{"providerId":"password","email":"volunteer@test.com","federatedId":"volunteer@test.com","rawId":"volunteer@test.com"}],"lastRefreshAt":"2022-03-04T01:12:31.436Z"},{"localId":"ROQ73OhakUeI6d41fRuw5hEgIl9e","createdAt":"1646356238569","lastLoginAt":"1646356238569","emailVerified":false,"email":"lead@test.com","salt":"fakeSaltKGQaBIRb6W2hYgVacK3Y","passwordHash":"fakeHash:salt=fakeSaltKGQaBIRb6W2hYgVacK3Y:password=testtesttest","passwordUpdatedAt":1646356238569,"validSince":"1646356238","providerUserInfo":[{"providerId":"password","email":"lead@test.com","federatedId":"lead@test.com","rawId":"lead@test.com"}],"lastRefreshAt":"2022-03-04T01:10:38.569Z"}]}